applipy_prometheus/__init__.py
applipy_prometheus/endpoint.py
applipy_prometheus/module.py
applipy_prometheus/version.py
applipy_prometheus/wrapper.py
applipy_prometheus-1.1.3.dist-info/LICENSE
applipy_prometheus-1.1.3.dist-info/METADATA
applipy_prometheus-1.1.3.dist-info/WHEEL
applipy_prometheus-1.1.3.dist-info/top_level.txt
applipy_prometheus-1.1.3.dist-info/RECORD
