Metadata-Version: 2.1
Name: applipy-prometheus
Version: 1.1.3
Summary: Exposes applipy metrics in prometheus format
Home-page: https://gitlab.com/applipy/applipy_prometheus
Author: Alessio Linares
Author-email: mail@alessio.cc
License: Apache 2.0
Project-URL: Source, https://gitlab.com/applipy/applipy_prometheus
Platform: UNKNOWN
Classifier: Development Status :: 5 - Production/Stable
Classifier: Intended Audience :: Developers
Classifier: License :: OSI Approved :: Apache Software License
Classifier: Programming Language :: Python :: 3.6
Classifier: Programming Language :: Python :: 3.7
Classifier: Programming Language :: Python :: 3.8
Classifier: Topic :: Software Development :: Libraries
Requires-Python: >=3.6
Requires-Dist: applipy-http (<3.0.0,>=1.0.0)
Requires-Dist: applipy-metrics (<2.0.0,>=1.0.0)
